com/__init__.py
com/globalphasing/__init__.py
com/globalphasing/startools/__init__.py
com/globalphasing/startools/star_regex.py
com/globalphasing/startools/star_token_types.py
com/pdbe/__init__.py
com/pdbe/mmciftools/__init__.py
mmCif/__init__.py
mmCif/mmcifIO.py
mmCif/ordereddict.py
mmCif/utils.py
pdbecif/__init__.py
pdbecif/mmcif.py
pdbecif/mmcif_io.py
pdbecif/mmcif_tools.py
pdbecif/ordereddict.py
pdbecif/utils.py
pdbecif/globalphasing/__init__.py
pdbecif/globalphasing/startools/__init__.py
pdbecif/globalphasing/startools/star_regex.py
pdbecif/globalphasing/startools/star_token_types.py
PDBeCif-1.5.dist-info/LICENSE
PDBeCif-1.5.dist-info/METADATA
PDBeCif-1.5.dist-info/WHEEL
PDBeCif-1.5.dist-info/top_level.txt
PDBeCif-1.5.dist-info/RECORD
