Metadata-Version: 2.1
Name: PDBeCif
Version: 1.5
Summary: A lightweight pure python package for reading, writing and manipulating mmCIF files distributed by the wwPDB.
Home-page: http://pypi.python.org/pypi/PDBeCIF/
Author: Glen van Ginkel (Protein Data Bank in Europe; PDBe)
Author-email: pdbe@ebi.ac.uk
License: UNKNOWN
Project-URL: Source code, https://github.com/PDBeurope/pdbecif
Project-URL: Documentation, https://pdbeurope.github.io/pdbecif/
Keywords: STAR CIF mmCIF PDB PDBe parsing parser API
Platform: UNKNOWN
Classifier: License :: OSI Approved :: GNU General Public License v3 (GPLv3)
Classifier: Programming Language :: Python
Classifier: Programming Language :: Python :: 2
Classifier: Programming Language :: Python :: 2.6
Classifier: Programming Language :: Python :: 2.7
Classifier: Programming Language :: Python :: 3
Classifier: Programming Language :: Python :: 3.2
Classifier: Programming Language :: Python :: 3.3
Classifier: Programming Language :: Python :: 3.4
Classifier: Programming Language :: Python :: 3.5
Classifier: Programming Language :: Python :: 3.6
Classifier: Programming Language :: Python :: 3.7
Classifier: Programming Language :: Python :: Implementation :: CPython
Classifier: Programming Language :: Python :: Implementation :: PyPy
Classifier: Operating System :: Unix
Classifier: Operating System :: MacOS
Classifier: Operating System :: POSIX
Classifier: Intended Audience :: Science/Research
Classifier: Intended Audience :: Developers
Classifier: Topic :: Scientific/Engineering :: Bio-Informatics
